llm_cache/__init__.py
llm_cache/config.py
llm_cache/cache/__init__.py
llm_cache/cache/key_generator.py
llm_cache/cache/redis_storage.py
llm_cache/cache/sqlite_storage.py
llm_cache/cache/storage.py
llm_cache/proxy/__init__.py
llm_cache/proxy/server.py
llm_cache/wrapper/__init__.py
llm_cache/wrapper/sdk.py
llm_caching-0.1.1.dist-info/METADATA
llm_caching-0.1.1.dist-info/WHEEL
llm_caching-0.1.1.dist-info/entry_points.txt
llm_caching-0.1.1.dist-info/licenses/LICENSE
llm_caching-0.1.1.dist-info/RECORD
